instaspam/__init__.py
instaspam/__main__.py
instaspam2-1.3.dist-info/LICENSE
instaspam2-1.3.dist-info/METADATA
instaspam2-1.3.dist-info/WHEEL
instaspam2-1.3.dist-info/top_level.txt
instaspam2-1.3.dist-info/RECORD
