Metadata-Version: 2.1
Name: instaspam2
Version: 1.3
Summary: Python IsntaBot for spaming
Home-page: https://github.com/pypa/instaspam2
Author: sm02present , SM02
Author-email: rajnikantmahato@gmail.com
License: UNKNOWN
Project-URL: Bug Tracker, https://github.com/pypa/instaspam2/issues
Platform: UNKNOWN
Classifier: Programming Language :: Python :: 3
Classifier: Programming Language :: Python :: 3.5
Classifier: Programming Language :: Python :: 3.7
Classifier: License :: OSI Approved :: MIT License
Classifier: Operating System :: OS Independent
Requires-Python: >=3.5
License-File: LICENSE
